cams_ncp_client/__init__.py
cams_ncp_client/_base.py
cams_ncp_client/cams_file.py
cams_ncp_client/chimere_file.py
cams_ncp_client/client.py
cams_ncp_client/ecmwf_file.py
cams_ncp_client/forecast.py
cams_ncp_client/health.py
cams_ncp_client/model.py
cams_ncp_client/observation.py
cams_ncp_client/quantity.py
cams_ncp_client/schemas/__init__.py
cams_ncp_client/schemas/common.py
cams_ncp_client/station.py
cams_ncp_client/utils/__init__.py
cams_ncp_client/utils/cams_utils.py
cams_ncp_client/utils/chimere_utils.py
cams_ncp_client/utils/pandas_utils.py
cams_ncp_client/utils/request_utils.py
cams_ncp_client/utils/string_utils.py
cams_ncp_client-0.5.6.dist-info/LICENSE.md
cams_ncp_client-0.5.6.dist-info/METADATA
cams_ncp_client-0.5.6.dist-info/WHEEL
cams_ncp_client-0.5.6.dist-info/RECORD
