Metadata-Version: 2.1
Name: cams-ncp-client
Version: 0.5.6
Summary: Python Client for the CAMS NCP API.
Author: Roeland Maes
Author-email: roeland.maes@vito.be
Requires-Python: >=3.10,<4.0
Classifier: Programming Language :: Python :: 3
Classifier: Programming Language :: Python :: 3.10
Classifier: Programming Language :: Python :: 3.11
Classifier: Programming Language :: Python :: 3.12
Provides-Extra: full
Provides-Extra: loguru
Provides-Extra: ruff
Provides-Extra: sphinx
Provides-Extra: xarray
Requires-Dist: SASAIR (>=0.2.3)
Requires-Dist: h5netcdf (>=1.6) ; extra == "xarray" or extra == "full"
Requires-Dist: loguru (>=0.7,<0.8) ; extra == "loguru" or extra == "full"
Requires-Dist: myst_parser (>=3.0) ; extra == "sphinx" or extra == "full"
Requires-Dist: pandas (>=1.5)
Requires-Dist: pydantic (>=2.0,<3.0)
Requires-Dist: requests (>=2.31,<3.0)
Requires-Dist: ruff (>=0.2,<0.3) ; extra == "ruff" or extra == "full"
Requires-Dist: scikit-learn (>=1.4.2,<2.0.0) ; extra == "full"
Requires-Dist: sphinx (>=8.1) ; extra == "sphinx" or extra == "full"
Requires-Dist: sphinx-autodoc-typehints (>=3.0) ; extra == "sphinx" or extra == "full"
Requires-Dist: sphinx_rtd_theme (>=1.0) ; extra == "sphinx" or extra == "full"
Requires-Dist: tomli (>=2.1) ; extra == "sphinx" or extra == "full"
Requires-Dist: xarray (>=2023.1) ; extra == "xarray" or extra == "full"
